cdiffer.cpython-39-darwin.so
src/cdiffer.o
cdiffer-0.7.2.dist-info/LICENSE
cdiffer-0.7.2.dist-info/METADATA
cdiffer-0.7.2.dist-info/WHEEL
cdiffer-0.7.2.dist-info/top_level.txt
cdiffer-0.7.2.dist-info/RECORD
