Metadata-Version: 2.1
Name: cdiffer
Version: 0.7.2
Summary: Edit distance, Similarity and 2 sequence differences printing
Home-page: https://github.com/kirin123kirin/cdiffer
Author: kirin123kirin
License: MIT
Keywords: diff,comparison,compare,editdistance
Platform: Windows
Platform: Linux
Platform: Mac OS-X
Classifier: Development Status :: 5 - Production/Stable
Classifier: License :: OSI Approved :: MIT License
Classifier: Programming Language :: C
Classifier: Programming Language :: Python :: 3.6
Classifier: Programming Language :: Python :: 3.7
Classifier: Programming Language :: Python :: 3.8
Classifier: Programming Language :: Python :: 3.9
Classifier: Programming Language :: Python :: Implementation :: CPython
Classifier: Operating System :: OS Independent
Classifier: Operating System :: Microsoft :: Windows
Classifier: Operating System :: MacOS
Classifier: Operating System :: POSIX
License-File: LICENSE
